ProgressivePostgres/__init__.py
ProgressivePostgres/cache.py
ProgressivePostgres/client.py
ProgressivePostgres/config.py
ProgressivePostgres/logger.py
progressivepostgres-0.0.8.dist-info/METADATA
progressivepostgres-0.0.8.dist-info/WHEEL
progressivepostgres-0.0.8.dist-info/licenses/LICENSE
progressivepostgres-0.0.8.dist-info/RECORD
