Metadata-Version: 2.4
Name: ProgressivePostgres
Version: 0.0.8
Summary: A TimescaleDB client library with environment-based config and time-series data handling.
Author-email: Jakob Friedl <jakob.friedl@tuwien.ac.at>
License-Expression: MIT
License-File: LICENSE
Keywords: mqtt,postgresql,time-series,timescale,timestamp
Classifier: Development Status :: 2 - Pre-Alpha
Classifier: Intended Audience :: Developers
Classifier: License :: OSI Approved :: MIT License
Classifier: Operating System :: OS Independent
Classifier: Programming Language :: Python :: 3
Classifier: Programming Language :: Python :: 3.6
Classifier: Programming Language :: Python :: 3.7
Classifier: Programming Language :: Python :: 3.8
Classifier: Programming Language :: Python :: 3.9
Classifier: Topic :: Communications :: Telephony
Classifier: Topic :: Software Development :: Libraries :: Python Modules
Requires-Python: >=3.6
Requires-Dist: psycopg2-binary>=2.9.10
Requires-Dist: python-dotenv>=0.19.2
Requires-Dist: zeitgleich>=0.0.3
